data_agent_osisoft_pi/__init__.py
data_agent_osisoft_pi/connector.py
data_agent_osisoft_pi-0.4.1.dist-info/LICENSE.txt
data_agent_osisoft_pi-0.4.1.dist-info/METADATA
data_agent_osisoft_pi-0.4.1.dist-info/WHEEL
data_agent_osisoft_pi-0.4.1.dist-info/entry_points.txt
data_agent_osisoft_pi-0.4.1.dist-info/top_level.txt
data_agent_osisoft_pi-0.4.1.dist-info/RECORD
