Metadata-Version: 2.1
Name: data-agent-osisoft-pi
Version: 0.4.1
Summary: Osisoft PI historian plugin for `data-agent` package
Home-page: https://github.com/imubit/data-agent-osisoft-pi/
Author: Meir Tseitlin
Author-email: meir@imubit.com
License: LGPL v3
Project-URL: Documentation, https://github.com/imubit/data-agent-osisoft-pi/
Project-URL: Source, https://github.com/imubit/data-agent-osisoft-pi/
Project-URL: Download, https://pypi.org/project/data-agent-osisoft-pi/#files
Platform: any
Classifier: Development Status :: 4 - Beta
Classifier: Programming Language :: Python
License-File: LICENSE.txt
Requires-Dist: pandas
Requires-Dist: numpy
Requires-Dist: pythonnet
Requires-Dist: importlib-metadata ; python_version < "3.8"
Provides-Extra: testing
Requires-Dist: setuptools ; extra == 'testing'
Requires-Dist: pytest ; extra == 'testing'
Requires-Dist: pytest-cov ; extra == 'testing'
